{"gameVersion": "1.1.12","gameId": "08d172c6-4334-4a34-8f8e-e961ac8f4df0","gameSavedAt": "2021-02-23T15:41:06.774Z","gameStartedAt": "2021-02-23T15:40:27.489Z","gameEndedAt": null,"totalTimePlayed": "PT20.426S","players": [{"playerId": null,"color": 0,"control": "AI"},{"playerId": null,"color": 1,"control": "AI"}],"currentTurn": 4,"pieces": [{"id": "7c17143b-bfc5-4390-a950-5882aa9ffcb6","type": "rook","x": 0,"y": 7,"player": 0,"firstMove": true,"queenSide": true,"kingSide": false},{"id": "2eead8f3-e96d-4ca9-b553-a9f5a6a34187","type": "knight","x": 1,"y": 7,"player": 0,"queenSide": false,"kingSide": true},{"id": "06f6c816-4370-45e5-89b3-c992c8f6779b","type": "bishop","x": 2,"y": 7,"player": 0,"queenSide": false,"kingSide": true},{"id": "172938e9-225a-46c4-81c9-d9aa2f1edafe","type": "queen","x": 3,"y": 7,"player": 0,"queenSide": false,"kingSide": true},{"id": "c9a17dd7-0a3b-4167-926e-12cb0a4c07a6","type": "king","x": 4,"y": 7,"player": 0,"firstMove": true,"queenSide": true,"kingSide": false},{"id": "d3b2feab-76f7-44a3-a072-db7a8f24566f","type": "bishop","x": 5,"y": 7,"player": 0,"queenSide": false,"kingSide": true},{"id": "bf3029a8-31fb-437f-b6fc-32326504417a","type": "knight","x": 6,"y": 7,"player": 0,"queenSide": false,"kingSide": true},{"id": "e860c8ef-8dd7-4081-a6d0-f04e1a45559b","type": "rook","x": 7,"y": 7,"player": 0,"firstMove": true,"queenSide": false,"kingSide": true},{"id": "038875ca-601c-424d-8e97-1c60387caec7","type": "pawn","x": 0,"y": 6,"player": 0,"firstMove": true,"queenSide": true,"kingSide": false},{"id": "938e9540-2558-4f5b-9aa6-e6252f0739f0","type": "pawn","x": 1,"y": 6,"player": 0,"firstMove": true,"queenSide": false,"kingSide": true},{"id": "bfefce7b-24fe-4fef-9641-c2316e2c2a6f","type": "pawn","x": 2,"y": 6,"player": 0,"firstMove": true,"queenSide": false,"kingSide": true},{"id": "922159fc-c26b-45ab-aad5-2a967605a163","type": "pawn","x": 3,"y": 6,"player": 0,"firstMove": true,"queenSide": false,"kingSide": true},{"id": "3a515fea-0352-40b3-a108-79a5c6b7215f","type": "pawn","x": 5,"y": 6,"player": 0,"firstMove": true,"queenSide": false,"kingSide": true},{"id": "5bd40f68-29c2-46dd-84fd-a2c82a258d8c","type": "pawn","x": 6,"y": 6,"player": 0,"firstMove": true,"queenSide": false,"kingSide": true},{"id": "684f29ad-b29f-4dbe-b509-d671cbc848b0","type": "pawn","x": 7,"y": 6,"player": 0,"firstMove": true,"queenSide": false,"kingSide": true},{"id": "96b822c4-75e5-4e6a-bf47-66875ec54a05","type": "pawn","x": 3,"y": 3,"player": 0,"firstMove": false,"queenSide": true,"kingSide": false},{"id": "2d095eaa-c1fe-43fe-a7af-171f5e888b01","type": "pawn","x": 0,"y": 1,"player": 1,"firstMove": true,"queenSide": true,"kingSide": false},{"id": "debb4320-5057-4922-8ca0-171b7b89dbb0","type": "pawn","x": 1,"y": 1,"player": 1,"firstMove": true,"queenSide": false,"kingSide": true},{"id": "13125061-1748-446d-8b59-3fe02502a240","type": "pawn","x": 2,"y": 1,"player": 1,"firstMove": true,"queenSide": false,"kingSide": true},{"id": "ab0faa08-87f6-4f46-ac51-7e207a268ef5","type": "pawn","x": 4,"y": 1,"player": 1,"firstMove": true,"queenSide": true,"kingSide": false},{"id": "02b6a386-35e1-49e4-ad97-51c5cc42dfe1","type": "pawn","x": 5,"y": 1,"player": 1,"firstMove": true,"queenSide": false,"kingSide": true},{"id": "177bc95a-6e0b-4e5e-98b0-8e50ab27842d","type": "pawn","x": 6,"y": 1,"player": 1,"firstMove": true,"queenSide": false,"kingSide": true},{"id": "56074699-16bd-47a5-81c2-7d54e70d0ac8","type": "pawn","x": 7,"y": 1,"player": 1,"firstMove": true,"queenSide": false,"kingSide": true},{"id": "c8943ed2-a2f1-4fe5-bf7e-cf69ce87dc7f","type": "rook","x": 0,"y": 0,"player": 1,"firstMove": true,"queenSide": true,"kingSide": false},{"id": "8eea0b48-776d-4d56-be8a-5d4a99328011","type": "knight","x": 1,"y": 0,"player": 1,"queenSide": false,"kingSide": true},{"id": "5f1503e9-22e1-4bf0-9225-16a7bb8f2400","type": "bishop","x": 2,"y": 0,"player": 1,"queenSide": false,"kingSide": true},{"id": "3b3171d3-dcf8-4758-84ec-b6b59ce6c316","type": "queen","x": 3,"y": 0,"player": 1,"queenSide": false,"kingSide": true},{"id": "d644e4eb-5f6e-4aaf-af5a-82d3b0fe1361","type": "king","x": 4,"y": 0,"player": 1,"firstMove": true,"queenSide": true,"kingSide": false},{"id": "4174a312-7d5b-4019-a3bf-2ff024749702","type": "bishop","x": 5,"y": 0,"player": 1,"queenSide": false,"kingSide": true},{"id": "c067239a-500f-4988-bcf1-a44a13ef06b9","type": "knight","x": 5,"y": 2,"player": 1,"firstMove": false,"queenSide": false,"kingSide": true},{"id": "38979a4e-d5a0-4eaf-bb0f-ec5f47c68594","type": "rook","x": 7,"y": 0,"player": 1,"firstMove": true,"queenSide": false,"kingSide": true}],"removedPieces": [[],[{"id": "cad95d76-805f-4529-9985-ad72e1a39907","type": "pawn","x": 3,"y": 3,"player": 1,"firstMove": false,"queenSide": false,"kingSide": true}]],"enPassantTarget": null,"allowNoKing": false,"aiSettings": [{"name": "Skill Level","value": 10},{"name": "Depth","value": 14},{"name": "Contempt","value": 21},{"name": "Analysis Contempt","value": "Both"},{"name": "MultiPV","value": 1},{"name": "Minimum Thinking Time","value": 20},{"name": "Slow Mover","value": 84},{"name": "UCI_Variant","value": "chess"},{"name": "Ponder","value": false},{"name": "UCI_Chess960","value": true},{"name": "UCI_AnalyseMode","value": true}]}