{"gameVersion": "1.1.12","gameId": "183826fd-75bd-46fd-80db-de5ce6a407d6","gameSavedAt": "2020-09-22T04:47:34.870Z","gameStartedAt": "2020-09-22T04:47:02.292Z","gameEndedAt": null,"totalTimePlayed": "PT32.076S","players": [{"playerId": "da1ef0af-8539-4883-b291-497518b49abb","color": 0,"control": "Human"},{"playerId": null,"color": 1,"control": "Human"}],"currentTurn": 11,"pieces": [{"id": "9a9c764f-2a72-4705-8988-107b4ab9bd7f","type": "pawn","x": 0,"y": 6,"player": 0,"firstMove": true,"queenSide": true,"kingSide": false},{"id": "3cf64649-1689-4a3b-b991-669831756754","type": "rook","x": 0,"y": 7,"player": 0,"firstMove": true,"queenSide": true,"kingSide": false},{"id": "247762ea-09d3-42b5-9fe8-4b4b2b3ae2ae","type": "pawn","x": 1,"y": 6,"player": 0,"firstMove": true,"queenSide": false,"kingSide": true},{"id": "fd7647f1-5af1-4daa-ba0a-4f417d781065","type": "knight","x": 1,"y": 7,"player": 0,"queenSide": false,"kingSide": true},{"id": "3293f2b2-5f35-4cda-ba40-52df313f5fc7","type": "pawn","x": 2,"y": 6,"player": 0,"firstMove": true,"queenSide": false,"kingSide": true},{"id": "91172d8e-0183-47ff-aab4-d1d261e3aca8","type": "bishop","x": 2,"y": 7,"player": 0,"queenSide": false,"kingSide": true},{"id": "65df3420-ece4-4fed-881a-3e3541902f74","type": "pawn","x": 3,"y": 4,"player": 0,"firstMove": false,"queenSide": false,"kingSide": true},{"id": "5133782c-7744-44f3-a1c8-6089603fa2bb","type": "queen","x": 3,"y": 7,"player": 0,"queenSide": false,"kingSide": true},{"id": "62f8ecd6-fa51-4efa-8ce8-8017d31ee452","type": "king","x": 4,"y": 7,"player": 0,"firstMove": true,"queenSide": true,"kingSide": false},{"id": "c6ff9fa7-bca3-468e-9f22-2d16e56b7388","type": "bishop","x": 5,"y": 7,"player": 0,"queenSide": false,"kingSide": true},{"id": "6df7a87f-64d3-44b4-8a56-58bfa76dcc65","type": "knight","x": 6,"y": 7,"player": 0,"queenSide": false,"kingSide": true},{"id": "780c2d6e-725b-46ad-99d3-8ae7af7039f3","type": "pawn","x": 7,"y": 4,"player": 0,"firstMove": false,"queenSide": false,"kingSide": true},{"id": "873544da-25a1-4f6f-923b-c75a60888e3c","type": "rook","x": 7,"y": 7,"player": 0,"firstMove": true,"queenSide": false,"kingSide": true},{"id": "e14f287f-a5ba-4b4c-87d1-e68347c44a48","type": "pawn","x": 0,"y": 1,"player": 1,"firstMove": true,"queenSide": true,"kingSide": false},{"id": "130f9592-ae69-4879-827e-dc8208dbc7b7","type": "rook","x": 0,"y": 0,"player": 1,"firstMove": true,"queenSide": true,"kingSide": false},{"id": "5fc6b8f2-aa83-4045-8d8d-8dc29aef54ac","type": "pawn","x": 1,"y": 1,"player": 1,"firstMove": true,"queenSide": false,"kingSide": true},{"id": "f4430ac0-c2ed-46c2-b76b-dc9063e05db4","type": "knight","x": 1,"y": 0,"player": 1,"queenSide": false,"kingSide": true},{"id": "7048c02e-bb98-4b70-af7e-f993826ab2a4","type": "pawn","x": 2,"y": 1,"player": 1,"firstMove": true,"queenSide": false,"kingSide": true},{"id": "50092366-4b76-4d20-aa9e-5f21331260a2","type": "bishop","x": 2,"y": 0,"player": 1,"queenSide": false,"kingSide": true},{"id": "1b8b32f5-cd67-4ac1-a2dd-31486a2f9cbc","type": "pawn","x": 6,"y": 6,"player": 1,"firstMove": false,"queenSide": false,"kingSide": true},{"id": "b1e4ae95-417a-4667-bbb1-61eedaecdb35","type": "queen","x": 3,"y": 0,"player": 1,"queenSide": false,"kingSide": true},{"id": "b2d47b36-8c74-47c0-91f7-207079caa563","type": "pawn","x": 4,"y": 1,"player": 1,"firstMove": true,"queenSide": true,"kingSide": false},{"id": "33358c00-cb90-4a11-b7d8-1f35671d5b0c","type": "king","x": 4,"y": 0,"player": 1,"firstMove": true,"queenSide": true,"kingSide": false},{"id": "54744971-8d51-44e3-8701-9e8ac4e372dd","type": "pawn","x": 5,"y": 1,"player": 1,"firstMove": true,"queenSide": false,"kingSide": true},{"id": "9ea0247b-7a4d-4f0a-b9c9-b3392047725f","type": "bishop","x": 5,"y": 0,"player": 1,"queenSide": false,"kingSide": true},{"id": "f2222a22-a9c3-4950-8832-f22822af50e6","type": "pawn","x": 6,"y": 1,"player": 1,"firstMove": true,"queenSide": false,"kingSide": true},{"id": "fdd43e06-8441-4ee9-b6c2-46cfddecde7c","type": "knight","x": 6,"y": 0,"player": 1,"queenSide": false,"kingSide": true},{"id": "0b2e422c-abb9-4429-97da-55275945ec7d","type": "pawn","x": 7,"y": 1,"player": 1,"firstMove": true,"queenSide": false,"kingSide": true},{"id": "cedbfe41-6743-4735-8427-9546b89c48cd","type": "rook","x": 7,"y": 0,"player": 1,"firstMove": true,"queenSide": false,"kingSide": true}],"removedPieces": [[{"id": "3b7bda11-3e66-4483-81ec-a95275e884e2","type": "pawn","x": 4,"y": 4,"player": 0,"firstMove": false,"queenSide": true,"kingSide": false},{"id": "e15c1b24-414d-459f-953d-557a4881b92a","type": "pawn","x": 5,"y": 5,"player": 0,"firstMove": false,"queenSide": false,"kingSide": true},{"id": "9899e12d-ce99-4200-a4a3-d28ccc1c4531","type": "pawn","x": 6,"y": 6,"player": 0,"firstMove": true,"queenSide": false,"kingSide": true}],[]],"enPassantTarget": null,"allowNoKing": false,"aiSettings": [{"name": "Skill Level","value": 10},{"name": "Depth","value": 14},{"name": "Contempt","value": 21},{"name": "Analysis Contempt","value": "Both"},{"name": "MultiPV","value": 1},{"name": "Minimum Thinking Time","value": 20},{"name": "Slow Mover","value": 84},{"name": "UCI_Variant","value": "chess"},{"name": "Ponder","value": false},{"name": "UCI_Chess960","value": true},{"name": "UCI_AnalyseMode","value": true}]}