{"gameVersion": "1.1.12","gameId": "1a0d031d-3233-4c38-85a1-952622021936","gameSavedAt": "2021-02-26T07:30:53.966Z","gameStartedAt": "2021-02-26T07:28:42.865Z","gameEndedAt": null,"totalTimePlayed": "PT2M8.092S","players": [{"color": 0,"control": "Human"},{"playerId": null,"color": 1,"control": "AI"}],"currentTurn": 17,"pieces": [{"id": "478fefbd-c850-43f1-b8c4-98a94034ce9e","type": "rook","x": 0,"y": 7,"player": 0,"firstMove": true,"queenSide": true,"kingSide": false},{"id": "2d2cca5c-2fbc-442c-ad66-d3dbc14c2b18","type": "knight","x": 1,"y": 7,"player": 0,"queenSide": false,"kingSide": true},{"id": "3b90af61-f04b-4098-b0ff-fc5b4b94a218","type": "bishop","x": 6,"y": 3,"player": 0,"firstMove": false,"queenSide": false,"kingSide": true},{"id": "9eb6d03c-b7ab-4719-97c6-23ea0307e2dd","type": "queen","x": 3,"y": 7,"player": 0,"queenSide": false,"kingSide": true},{"id": "58c8d292-e892-4000-919d-4938cb4b3c90","type": "rook","x": 5,"y": 7,"player": 0,"firstMove": false,"queenSide": false,"kingSide": true},{"id": "c67bb3b8-4374-499e-b9b8-c58914dd7a07","type": "king","x": 6,"y": 7,"player": 0,"firstMove": false,"queenSide": true,"kingSide": false},{"id": "123895e7-11c2-4948-bdb3-03a5206625ac","type": "pawn","x": 0,"y": 6,"player": 0,"firstMove": true,"queenSide": true,"kingSide": false},{"id": "a3169c14-3d11-4410-a096-1f4ffb83c07a","type": "pawn","x": 1,"y": 6,"player": 0,"firstMove": true,"queenSide": false,"kingSide": true},{"id": "dd38edbe-476e-4d7e-a10d-7efbbc7907b8","type": "pawn","x": 2,"y": 6,"player": 0,"firstMove": true,"queenSide": false,"kingSide": true},{"id": "61fd30f4-fe1c-4550-b417-d548cac78dab","type": "pawn","x": 5,"y": 6,"player": 0,"firstMove": true,"queenSide": false,"kingSide": true},{"id": "ff66b822-2ad1-423b-9069-54839414c82f","type": "pawn","x": 6,"y": 6,"player": 0,"firstMove": true,"queenSide": false,"kingSide": true},{"id": "d72b52ac-73ce-4094-b8e8-18be49d53e85","type": "pawn","x": 7,"y": 6,"player": 0,"firstMove": true,"queenSide": false,"kingSide": true},{"id": "a7fb389a-7037-4c24-a0d4-9bef5135163a","type": "bishop","x": 1,"y": 5,"player": 0,"firstMove": false,"queenSide": false,"kingSide": true},{"id": "e1a78527-6ae8-463c-aaa4-ed0c1f5b4dd9","type": "pawn","x": 3,"y": 5,"player": 0,"firstMove": false,"queenSide": false,"kingSide": true},{"id": "91b24d22-521a-49fb-b01c-dd82ecaeb562","type": "knight","x": 5,"y": 5,"player": 0,"firstMove": false,"queenSide": false,"kingSide": true},{"id": "6c01e066-2446-4213-995a-0a81e65d1785","type": "pawn","x": 4,"y": 4,"player": 0,"firstMove": false,"queenSide": true,"kingSide": false},{"id": "1707f37b-b14d-4451-8c42-3dce6954370a","type": "knight","x": 0,"y": 3,"player": 1,"firstMove": false,"queenSide": false,"kingSide": true},{"id": "78cc4075-88b9-4236-bbc3-5ba85536c4f2","type": "pawn","x": 1,"y": 3,"player": 1,"firstMove": false,"queenSide": false,"kingSide": true},{"id": "aefb120d-4027-4089-8704-6abd4ac70a5e","type": "pawn","x": 0,"y": 2,"player": 1,"firstMove": false,"queenSide": true,"kingSide": false},{"id": "d507f1f8-61ef-46a4-a02d-f1418d648191","type": "pawn","x": 3,"y": 2,"player": 1,"firstMove": false,"queenSide": false,"kingSide": true},{"id": "659d2f8c-0660-42f9-a22d-2bb8fbdb0e88","type": "pawn","x": 4,"y": 2,"player": 1,"firstMove": false,"queenSide": true,"kingSide": false},{"id": "238739f1-65ab-4a33-a9b9-12beae57b255","type": "knight","x": 5,"y": 2,"player": 1,"firstMove": false,"queenSide": false,"kingSide": true},{"id": "f99e799e-825d-4d0f-a7e8-62dae3d8488f","type": "pawn","x": 2,"y": 1,"player": 1,"firstMove": true,"queenSide": false,"kingSide": true},{"id": "18f8eff0-3b2c-4be6-866f-f609c61ef540","type": "pawn","x": 5,"y": 1,"player": 1,"firstMove": true,"queenSide": false,"kingSide": true},{"id": "70d1e39b-b192-4e16-87d8-bfda67e9a31b","type": "pawn","x": 6,"y": 1,"player": 1,"firstMove": true,"queenSide": false,"kingSide": true},{"id": "7a710f2a-9690-4606-9772-0b195c6c85d2","type": "pawn","x": 7,"y": 1,"player": 1,"firstMove": true,"queenSide": false,"kingSide": true},{"id": "8dacef5f-71df-4455-ab5b-941156bb0e99","type": "rook","x": 0,"y": 0,"player": 1,"firstMove": true,"queenSide": true,"kingSide": false},{"id": "81fb2da5-5c1e-4480-9386-e68e0a0cdd51","type": "bishop","x": 1,"y": 1,"player": 1,"firstMove": false,"queenSide": false,"kingSide": true},{"id": "22ed28dd-5853-4260-baf4-2a645c408486","type": "queen","x": 3,"y": 0,"player": 1,"queenSide": false,"kingSide": true},{"id": "37967b48-384e-4f89-a7a1-7fc3e79a521f","type": "king","x": 4,"y": 0,"player": 1,"firstMove": true,"queenSide": true,"kingSide": false},{"id": "9ba1e857-ee7f-4dae-8be2-84119c5c73ac","type": "bishop","x": 5,"y": 0,"player": 1,"queenSide": false,"kingSide": true},{"id": "1aeb9a5c-bcee-4c80-a997-bbdf5c4bc120","type": "rook","x": 7,"y": 0,"player": 1,"firstMove": true,"queenSide": false,"kingSide": true}],"removedPieces": [[],[]],"enPassantTarget": null,"allowNoKing": false,"aiSettings": [{"name": "Skill Level","value": 10},{"name": "Depth","value": 14},{"name": "Contempt","value": 21},{"name": "Analysis Contempt","value": "Both"},{"name": "MultiPV","value": 1},{"name": "Minimum Thinking Time","value": 20},{"name": "Slow Mover","value": 84},{"name": "UCI_Variant","value": "chess"},{"name": "Ponder","value": false},{"name": "UCI_Chess960","value": true},{"name": "UCI_AnalyseMode","value": true}]}