{"gameVersion": "1.1.12","gameId": "2dd6ff3b-e9b3-431f-a685-6e6b3da31a0f","gameSavedAt": "2020-05-18T18:36:27.727Z","gameStartedAt": "2020-05-18T18:36:14.694Z","gameEndedAt": null,"totalTimePlayed": "PT12.032S","players": [{"playerId": "1cd782fb-c11c-4061-8234-13fe5d8ec3cf","color": 0,"control": "Human"},{"playerId": null,"color": 1,"control": "Human"}],"currentTurn": 4,"pieces": [{"id": "eeb7746f-4d8c-4aa6-8341-9e88ddc9dbc9","type": "pawn","x": 0,"y": 6,"player": 0,"firstMove": true,"queenSide": true,"kingSide": false},{"id": "c14326da-f62f-4558-9510-637def80f013","type": "rook","x": 0,"y": 7,"player": 0,"firstMove": true,"queenSide": true,"kingSide": false},{"id": "5cf6dd3d-24c1-4cd8-9a6f-dd58959ae6a8","type": "pawn","x": 1,"y": 6,"player": 0,"firstMove": true,"queenSide": false,"kingSide": true},{"id": "018905d3-7da1-490f-84a3-cd2068544310","type": "knight","x": 1,"y": 7,"player": 0,"queenSide": false,"kingSide": true},{"id": "ed649be1-b55c-4518-a19c-112f08ae9a1f","type": "pawn","x": 2,"y": 6,"player": 0,"firstMove": true,"queenSide": false,"kingSide": true},{"id": "dd73e67e-e447-48c1-a59d-2292d2acda3b","type": "bishop","x": 2,"y": 7,"player": 0,"queenSide": false,"kingSide": true},{"id": "cab3dafc-55b8-4515-a919-fe3ae2db377f","type": "pawn","x": 3,"y": 5,"player": 0,"firstMove": false,"queenSide": false,"kingSide": true},{"id": "b25e4a66-1819-4a41-ad45-31fc8f9f1ba4","type": "queen","x": 3,"y": 7,"player": 0,"queenSide": false,"kingSide": true},{"id": "01a7674e-9296-494f-98a2-d57b85feef1b","type": "pawn","x": 4,"y": 4,"player": 0,"firstMove": false,"queenSide": true,"kingSide": false},{"id": "45689a42-8c06-4fd0-8604-d8d76ef377a2","type": "king","x": 4,"y": 7,"player": 0,"firstMove": true,"queenSide": true,"kingSide": false},{"id": "9f81178b-c26a-41fe-8e72-9b7d81bc575b","type": "pawn","x": 5,"y": 6,"player": 0,"firstMove": true,"queenSide": false,"kingSide": true},{"id": "1c40b0bf-cfde-4645-8804-5a4b18fb148a","type": "bishop","x": 5,"y": 7,"player": 0,"queenSide": false,"kingSide": true},{"id": "39396efb-03e9-48d1-b45d-147ca8246000","type": "pawn","x": 6,"y": 6,"player": 0,"firstMove": true,"queenSide": false,"kingSide": true},{"id": "ee4bd3b7-49de-4c02-bcf2-bce55783aefd","type": "knight","x": 6,"y": 7,"player": 0,"queenSide": false,"kingSide": true},{"id": "5e904b35-1a0c-4fcc-8cd3-f8507bebd4c9","type": "pawn","x": 7,"y": 6,"player": 0,"firstMove": true,"queenSide": false,"kingSide": true},{"id": "24e3f35c-e32c-4915-9fb5-4b6a52a6b711","type": "rook","x": 7,"y": 7,"player": 0,"firstMove": true,"queenSide": false,"kingSide": true},{"id": "37c76fa4-83da-46a6-84c7-bb38f71dba5b","type": "pawn","x": 0,"y": 1,"player": 1,"firstMove": true,"queenSide": true,"kingSide": false},{"id": "4f6ec916-aefc-45fe-8cb9-7fc4b6a1c4c9","type": "rook","x": 0,"y": 0,"player": 1,"firstMove": true,"queenSide": true,"kingSide": false},{"id": "104c9292-371e-4d65-ab58-7de7ac305d65","type": "pawn","x": 1,"y": 1,"player": 1,"firstMove": true,"queenSide": false,"kingSide": true},{"id": "968d5480-d725-49ef-9237-a1b9c7942d8d","type": "knight","x": 1,"y": 0,"player": 1,"queenSide": false,"kingSide": true},{"id": "c6c6840a-dd88-4846-b1f1-05a273e5f469","type": "pawn","x": 2,"y": 1,"player": 1,"firstMove": true,"queenSide": false,"kingSide": true},{"id": "3e2ea0dc-db56-4451-9fdc-ba26b592da41","type": "bishop","x": 2,"y": 0,"player": 1,"queenSide": false,"kingSide": true},{"id": "fb42737b-725c-481f-81b8-b7d3ccec8cb5","type": "pawn","x": 3,"y": 2,"player": 1,"firstMove": false,"queenSide": false,"kingSide": true},{"id": "7db6a40a-ef43-4964-a302-88f34b45e949","type": "queen","x": 3,"y": 0,"player": 1,"queenSide": false,"kingSide": true},{"id": "7aa46edf-1b2f-409f-b986-5d1924b4be90","type": "pawn","x": 4,"y": 3,"player": 1,"firstMove": false,"queenSide": true,"kingSide": false},{"id": "e250efde-3fdd-4a38-8472-7cce85f90b6a","type": "king","x": 4,"y": 0,"player": 1,"firstMove": true,"queenSide": true,"kingSide": false},{"id": "30263b6c-afdb-428c-b4fe-38332c573bc1","type": "pawn","x": 5,"y": 1,"player": 1,"firstMove": true,"queenSide": false,"kingSide": true},{"id": "59ca805b-ef9c-43d5-ad92-02fbe0ea9b48","type": "bishop","x": 5,"y": 0,"player": 1,"queenSide": false,"kingSide": true},{"id": "58c5e7fa-cffc-4559-9092-b6b09fdc2d80","type": "pawn","x": 6,"y": 1,"player": 1,"firstMove": true,"queenSide": false,"kingSide": true},{"id": "2d98507f-3f99-4813-8e0c-5b728dab1166","type": "knight","x": 6,"y": 0,"player": 1,"queenSide": false,"kingSide": true},{"id": "8dc9b002-b355-4fbf-9fec-37f9ffca8fe9","type": "pawn","x": 7,"y": 1,"player": 1,"firstMove": true,"queenSide": false,"kingSide": true},{"id": "c6fe23e0-7346-4fe5-ab83-a06b30554b12","type": "rook","x": 7,"y": 0,"player": 1,"firstMove": true,"queenSide": false,"kingSide": true}],"removedPieces": [[],[]],"enPassantTarget": {"x": 4,"y": 2},"allowNoKing": false,"aiSettings": [{"name": "Skill Level","value": 10},{"name": "Depth","value": 14},{"name": "Contempt","value": 21},{"name": "Analysis Contempt","value": "Both"},{"name": "MultiPV","value": 1},{"name": "Minimum Thinking Time","value": 20},{"name": "Slow Mover","value": 84},{"name": "UCI_Variant","value": "chess"},{"name": "Ponder","value": false},{"name": "UCI_Chess960","value": true},{"name": "UCI_AnalyseMode","value": true}]}