{"gameVersion": "1.1.12","gameId": "54a97267-a165-4391-b8d9-1776071f7786","gameSavedAt": "2020-08-08T14:33:18.767Z","gameStartedAt": "2020-08-08T14:33:03.577Z","gameEndedAt": null,"totalTimePlayed": "PT15.175S","players": [{"playerId": "72d3fdc9-d16e-4faf-a5b0-ae8d6b4000cd","color": 0,"control": "Human"},{"playerId": null,"color": 1,"control": "Human"}],"currentTurn": 2,"pieces": [{"id": "24acad3f-cd2a-4152-978f-844d9aed132b","type": "pawn","x": 0,"y": 6,"player": 0,"firstMove": true,"queenSide": true,"kingSide": false},{"id": "dbb6a814-2ba6-4e06-90f6-b6a910763e84","type": "rook","x": 0,"y": 7,"player": 0,"firstMove": true,"queenSide": true,"kingSide": false},{"id": "324e03fe-ffde-4f05-b69c-3ddc6b73794d","type": "pawn","x": 1,"y": 6,"player": 0,"firstMove": true,"queenSide": false,"kingSide": true},{"id": "63da47b5-e5b5-4c6e-8058-8f6ffba7eea2","type": "knight","x": 1,"y": 7,"player": 0,"queenSide": false,"kingSide": true},{"id": "6b482bf7-3697-48ca-82cf-1dc81c153066","type": "pawn","x": 2,"y": 4,"player": 0,"firstMove": false,"queenSide": false,"kingSide": true},{"id": "1b141e0e-c8c0-4d7e-abc3-1086f1749877","type": "bishop","x": 2,"y": 7,"player": 0,"queenSide": false,"kingSide": true},{"id": "740f0ef3-2ef5-449b-afae-5b2b66860737","type": "pawn","x": 3,"y": 6,"player": 0,"firstMove": true,"queenSide": false,"kingSide": true},{"id": "548ad156-fd24-4cc7-b7b5-4dff91162fbe","type": "queen","x": 3,"y": 7,"player": 0,"queenSide": false,"kingSide": true},{"id": "d01f20fb-5bc1-4709-a7c5-bd96e1b6dd20","type": "pawn","x": 4,"y": 6,"player": 0,"firstMove": true,"queenSide": true,"kingSide": false},{"id": "7dd23f9d-8e88-42bd-a347-a0ecc8c6dfdd","type": "king","x": 4,"y": 7,"player": 0,"firstMove": true,"queenSide": true,"kingSide": false},{"id": "b7ca87d2-18d3-4d77-b4d5-c1a009331630","type": "pawn","x": 5,"y": 6,"player": 0,"firstMove": true,"queenSide": false,"kingSide": true},{"id": "a12b472e-9ce7-4022-b1c2-d082ea02be68","type": "bishop","x": 5,"y": 7,"player": 0,"queenSide": false,"kingSide": true},{"id": "c79d20e6-c46b-4395-8e31-0cc65a07d235","type": "pawn","x": 6,"y": 6,"player": 0,"firstMove": true,"queenSide": false,"kingSide": true},{"id": "7b4033fb-5605-43a2-9a1c-bb9e587bd07e","type": "knight","x": 6,"y": 7,"player": 0,"queenSide": false,"kingSide": true},{"id": "d5bb4170-c55a-46fd-aef0-e87fea6532b0","type": "pawn","x": 7,"y": 6,"player": 0,"firstMove": true,"queenSide": false,"kingSide": true},{"id": "7e3e41b8-2190-481e-ac23-72750c636f86","type": "rook","x": 7,"y": 7,"player": 0,"firstMove": true,"queenSide": false,"kingSide": true},{"id": "705474d3-c9be-4b12-a30a-48223a85d34a","type": "pawn","x": 0,"y": 1,"player": 1,"firstMove": true,"queenSide": true,"kingSide": false},{"id": "447f27e2-7afc-499e-87be-e0c37f13e703","type": "rook","x": 0,"y": 0,"player": 1,"firstMove": true,"queenSide": true,"kingSide": false},{"id": "c4235f23-f754-40d8-9f27-feeb1b49c19a","type": "pawn","x": 1,"y": 1,"player": 1,"firstMove": true,"queenSide": false,"kingSide": true},{"id": "54a95fb1-509a-4ece-ad3a-fab52003a7c6","type": "knight","x": 1,"y": 0,"player": 1,"queenSide": false,"kingSide": true},{"id": "d8a943f7-3386-437a-a721-e2c228424778","type": "pawn","x": 2,"y": 1,"player": 1,"firstMove": true,"queenSide": false,"kingSide": true},{"id": "7bdae688-be96-4962-84e1-78ce92f1823c","type": "bishop","x": 2,"y": 0,"player": 1,"queenSide": false,"kingSide": true},{"id": "d50af262-dedb-409d-8a9e-ea53d3c5306a","type": "pawn","x": 3,"y": 1,"player": 1,"firstMove": true,"queenSide": false,"kingSide": true},{"id": "2a47ae5a-60dc-4396-a287-f547cad630a0","type": "queen","x": 3,"y": 0,"player": 1,"queenSide": false,"kingSide": true},{"id": "3da8c1ed-5a62-47e1-8c72-e31658f3cdbb","type": "pawn","x": 4,"y": 3,"player": 1,"firstMove": false,"queenSide": true,"kingSide": false},{"id": "01888a03-34d1-4f77-80a9-dd2e752bbf51","type": "king","x": 4,"y": 0,"player": 1,"firstMove": true,"queenSide": true,"kingSide": false},{"id": "3c47bc82-5490-476b-aa87-225998689f14","type": "pawn","x": 5,"y": 1,"player": 1,"firstMove": true,"queenSide": false,"kingSide": true},{"id": "202d84e5-af01-4ef4-aee4-00219f6f9e0f","type": "bishop","x": 5,"y": 0,"player": 1,"queenSide": false,"kingSide": true},{"id": "791c5182-1d4b-4a5f-af8c-e882c6d4e503","type": "pawn","x": 6,"y": 1,"player": 1,"firstMove": true,"queenSide": false,"kingSide": true},{"id": "9d1ec6a0-7e09-4983-bf69-96dafb68f0d0","type": "knight","x": 6,"y": 0,"player": 1,"queenSide": false,"kingSide": true},{"id": "6742129f-2d14-4fd0-a2a8-f8e9ba2018ad","type": "pawn","x": 7,"y": 1,"player": 1,"firstMove": true,"queenSide": false,"kingSide": true},{"id": "f8a1d797-a049-4da9-9446-16b8d36063e0","type": "rook","x": 7,"y": 0,"player": 1,"firstMove": true,"queenSide": false,"kingSide": true}],"removedPieces": [[],[]],"enPassantTarget": {"x": 4,"y": 2},"allowNoKing": false,"aiSettings": [{"name": "Skill Level","value": 10},{"name": "Depth","value": 14},{"name": "Contempt","value": 21},{"name": "Analysis Contempt","value": "Both"},{"name": "MultiPV","value": 1},{"name": "Minimum Thinking Time","value": 20},{"name": "Slow Mover","value": 84},{"name": "UCI_Variant","value": "chess"},{"name": "Ponder","value": false},{"name": "UCI_Chess960","value": true},{"name": "UCI_AnalyseMode","value": true}]}