{"gameVersion": "1.1.12","gameId": "5e88f824-1dcd-4d07-aa09-b706e8a9f06a","gameSavedAt": "2021-03-03T18:39:31.075Z","gameStartedAt": "2021-03-03T18:39:08.326Z","gameEndedAt": null,"totalTimePlayed": "PT22.024S","players": [{"playerId": null,"color": 0,"control": "Human"},{"playerId": null,"color": 1,"control": "Human"}],"currentTurn": 3,"pieces": [{"id": "e999c3a9-0272-4561-8b66-261e42903688","type": "pawn","x": 0,"y": 6,"player": 0,"firstMove": true,"queenSide": true,"kingSide": false},{"id": "b36ab7b6-0f3d-4f14-b18f-e716a7bfcf25","type": "rook","x": 0,"y": 7,"player": 0,"firstMove": true,"queenSide": true,"kingSide": false},{"id": "e7f03489-1a20-4a23-b0d1-79a977e5d28b","type": "pawn","x": 1,"y": 6,"player": 0,"firstMove": true,"queenSide": false,"kingSide": true},{"id": "25ad1da4-c48f-4d80-b380-e1d1575ce979","type": "knight","x": 1,"y": 7,"player": 0,"queenSide": false,"kingSide": true},{"id": "2bc7982c-48a3-4d84-afa9-e15aad609f0a","type": "pawn","x": 2,"y": 6,"player": 0,"firstMove": true,"queenSide": false,"kingSide": true},{"id": "5b8f399e-8497-4902-96b9-53233f6b6bc9","type": "bishop","x": 2,"y": 7,"player": 0,"queenSide": false,"kingSide": true},{"id": "1fd3910f-3ca7-4232-81e8-b13adab5cacc","type": "pawn","x": 3,"y": 6,"player": 0,"firstMove": true,"queenSide": false,"kingSide": true},{"id": "1fd355f6-25d7-490d-b210-915f264b1e0a","type": "queen","x": 3,"y": 7,"player": 0,"queenSide": false,"kingSide": true},{"id": "365bcc44-4872-4243-b309-6ea6ba9cbe75","type": "pawn","x": 4,"y": 6,"player": 0,"firstMove": true,"queenSide": true,"kingSide": false},{"id": "6888a0bc-8950-4f5c-994b-80addcd4b6d4","type": "king","x": 4,"y": 7,"player": 0,"firstMove": true,"queenSide": true,"kingSide": false},{"id": "528a5206-3665-46c5-8595-591060afcf56","type": "pawn","x": 5,"y": 4,"player": 0,"firstMove": false,"queenSide": false,"kingSide": true},{"id": "3aa21ba3-4613-4ea8-b72c-dfd1285a7a52","type": "bishop","x": 5,"y": 7,"player": 0,"queenSide": false,"kingSide": true},{"id": "419d3d11-4b9d-4d38-9080-b6f4d2f0cd36","type": "pawn","x": 6,"y": 6,"player": 0,"firstMove": true,"queenSide": false,"kingSide": true},{"id": "a85c8d4d-1a55-4e86-9fcb-55221f7f51f9","type": "knight","x": 5,"y": 5,"player": 0,"firstMove": false,"queenSide": false,"kingSide": true},{"id": "b6a4790e-4430-4b73-8aaa-a4210d9376c1","type": "pawn","x": 7,"y": 6,"player": 0,"firstMove": true,"queenSide": false,"kingSide": true},{"id": "32882924-97b3-4b54-a4c4-35b5af3993fb","type": "rook","x": 7,"y": 7,"player": 0,"firstMove": true,"queenSide": false,"kingSide": true},{"id": "0fe9a997-7e6a-4751-9511-69400573a102","type": "pawn","x": 0,"y": 1,"player": 1,"firstMove": true,"queenSide": true,"kingSide": false},{"id": "10eaa12e-2376-4853-b23f-14c49476ac95","type": "rook","x": 0,"y": 0,"player": 1,"firstMove": true,"queenSide": true,"kingSide": false},{"id": "3c795552-25a7-4cbd-b313-fb1d5ccd2c33","type": "pawn","x": 1,"y": 1,"player": 1,"firstMove": true,"queenSide": false,"kingSide": true},{"id": "c5738282-81ab-4415-a06f-3e4a0e933cfe","type": "knight","x": 1,"y": 0,"player": 1,"queenSide": false,"kingSide": true},{"id": "3ff6acd5-e04c-47df-b349-f760db7630c3","type": "pawn","x": 2,"y": 1,"player": 1,"firstMove": true,"queenSide": false,"kingSide": true},{"id": "368b149e-4384-42d6-8c51-68a26d60cf85","type": "bishop","x": 2,"y": 0,"player": 1,"queenSide": false,"kingSide": true},{"id": "74950270-f9bf-4a9d-a499-27183e836d2b","type": "pawn","x": 3,"y": 3,"player": 1,"firstMove": false,"queenSide": false,"kingSide": true},{"id": "b7bf07ec-44ec-4a22-a401-b94d8b275c9c","type": "queen","x": 3,"y": 0,"player": 1,"queenSide": false,"kingSide": true},{"id": "49642b7f-2282-47e7-b947-27012aa6f300","type": "pawn","x": 4,"y": 1,"player": 1,"firstMove": true,"queenSide": true,"kingSide": false},{"id": "2109f314-f8ad-471c-80ac-c361d14da602","type": "king","x": 4,"y": 0,"player": 1,"firstMove": true,"queenSide": true,"kingSide": false},{"id": "9aa69e0d-719c-40f2-9d2e-dcf1d9d95be6","type": "pawn","x": 5,"y": 1,"player": 1,"firstMove": true,"queenSide": false,"kingSide": true},{"id": "52061fb2-3b83-4e79-a375-561555d1f612","type": "bishop","x": 5,"y": 0,"player": 1,"queenSide": false,"kingSide": true},{"id": "0691f5a4-d7eb-4c98-a33f-2f39666a588b","type": "pawn","x": 6,"y": 1,"player": 1,"firstMove": true,"queenSide": false,"kingSide": true},{"id": "cbaaabe9-4eed-46fd-8422-63ff295ccab8","type": "knight","x": 6,"y": 0,"player": 1,"queenSide": false,"kingSide": true},{"id": "f9ce5efb-6f31-458f-a7e7-c22f6db5853d","type": "pawn","x": 7,"y": 1,"player": 1,"firstMove": true,"queenSide": false,"kingSide": true},{"id": "90e4374a-a60b-4e7d-ad5b-247e737a03a4","type": "rook","x": 7,"y": 0,"player": 1,"firstMove": true,"queenSide": false,"kingSide": true}],"removedPieces": [[],[]],"enPassantTarget": null,"allowNoKing": false,"aiSettings": [{"name": "Skill Level","value": 10},{"name": "Depth","value": 14},{"name": "Contempt","value": 21},{"name": "Analysis Contempt","value": "Both"},{"name": "MultiPV","value": 1},{"name": "Minimum Thinking Time","value": 20},{"name": "Slow Mover","value": 84},{"name": "UCI_Variant","value": "chess"},{"name": "Ponder","value": false},{"name": "UCI_Chess960","value": true},{"name": "UCI_AnalyseMode","value": true}]}