{"gameVersion": "1.1.10","gameId": "7b6d9e90-9028-413b-88b0-9b4f71f202e7","gameSavedAt": "2020-05-08T15:56:31.586Z","gameStartedAt": "2020-05-08T15:56:27.587Z","gameEndedAt": null,"totalTimePlayed": "PT3.037S","players": [{"playerId": "70f88443-df71-4048-bf35-acba1df4ba73","color": 0,"control": "Human"},{"playerId": "8efa7b0e-20e3-486e-aabd-66275ebbc4d7","color": 1,"control": "Human"}],"currentTurn": 1,"pieces": [{"id": "d6bcae12-0925-45e2-816e-84b4b68075d0","type": "pawn","x": 0,"y": 6,"player": 0,"firstMove": true,"queenSide": true,"kingSide": false},{"id": "4135aaca-cf04-4cb7-84d4-a913183faf38","type": "rook","x": 0,"y": 7,"player": 0,"firstMove": true,"queenSide": true,"kingSide": false},{"id": "6b2c39d9-1816-48cd-8d86-912ea89f4c65","type": "pawn","x": 1,"y": 6,"player": 0,"firstMove": true,"queenSide": false,"kingSide": true},{"id": "449b9513-aae8-4107-95c4-6c0fe792c07f","type": "knight","x": 1,"y": 7,"player": 0,"queenSide": false,"kingSide": true},{"id": "1d0a5551-24e2-48c2-97e3-e55e7bc828ad","type": "pawn","x": 2,"y": 6,"player": 0,"firstMove": true,"queenSide": false,"kingSide": true},{"id": "a949123c-c8da-4c03-9220-12b38c92ff48","type": "bishop","x": 2,"y": 7,"player": 0,"queenSide": false,"kingSide": true},{"id": "178bd7ed-a036-4a35-bed5-b5c0101841ad","type": "pawn","x": 3,"y": 4,"player": 0,"firstMove": false,"queenSide": false,"kingSide": true},{"id": "ec220f8e-bdac-44a3-855f-873404b6b046","type": "queen","x": 3,"y": 7,"player": 0,"queenSide": false,"kingSide": true},{"id": "4e4f5288-52be-4076-815f-aadcc57466f7","type": "pawn","x": 4,"y": 6,"player": 0,"firstMove": true,"queenSide": true,"kingSide": false},{"id": "826ae7bb-82c2-488c-b67f-949b907e038c","type": "king","x": 4,"y": 7,"player": 0,"firstMove": true,"queenSide": true,"kingSide": false},{"id": "a3df9bfc-8fb3-4470-9cdc-f4106301bd9b","type": "pawn","x": 5,"y": 6,"player": 0,"firstMove": true,"queenSide": false,"kingSide": true},{"id": "f5dd1e96-cdf6-4d73-a90a-213b6d2ff752","type": "bishop","x": 5,"y": 7,"player": 0,"queenSide": false,"kingSide": true},{"id": "5a2e7323-364c-4b89-9209-b39d9f5bb8cd","type": "pawn","x": 6,"y": 6,"player": 0,"firstMove": true,"queenSide": false,"kingSide": true},{"id": "6efdfe72-627e-46f0-87c2-35299f3a211f","type": "knight","x": 6,"y": 7,"player": 0,"queenSide": false,"kingSide": true},{"id": "6dacd19f-ad75-4030-bc3b-b6566baf68d5","type": "pawn","x": 7,"y": 6,"player": 0,"firstMove": true,"queenSide": false,"kingSide": true},{"id": "38c1a12d-1471-47f9-b320-143e0e98a559","type": "rook","x": 7,"y": 7,"player": 0,"firstMove": true,"queenSide": false,"kingSide": true},{"id": "686be579-0ac6-433d-9401-f1edaf8b08e8","type": "pawn","x": 0,"y": 1,"player": 1,"firstMove": true,"queenSide": true,"kingSide": false},{"id": "ec0f9bea-bb8c-4340-8364-822cc9460828","type": "rook","x": 0,"y": 0,"player": 1,"firstMove": true,"queenSide": true,"kingSide": false},{"id": "6d2abca5-fa5b-415a-8e27-7cd36206a86c","type": "pawn","x": 1,"y": 1,"player": 1,"firstMove": true,"queenSide": false,"kingSide": true},{"id": "768c502b-c41b-4d18-a141-2b0025e9380f","type": "knight","x": 1,"y": 0,"player": 1,"queenSide": false,"kingSide": true},{"id": "b88d9c6c-72c9-4225-ae66-05efae4c482a","type": "pawn","x": 2,"y": 1,"player": 1,"firstMove": true,"queenSide": false,"kingSide": true},{"id": "01c8a29b-227d-4b98-b13d-d7c23e0626e2","type": "bishop","x": 2,"y": 0,"player": 1,"queenSide": false,"kingSide": true},{"id": "53ae489c-7867-4573-8930-b148ce3d7122","type": "pawn","x": 3,"y": 1,"player": 1,"firstMove": true,"queenSide": false,"kingSide": true},{"id": "a10c27b4-bc32-4f41-9e9b-639e7addb197","type": "queen","x": 3,"y": 0,"player": 1,"queenSide": false,"kingSide": true},{"id": "8162e40e-d255-42fe-bee3-ed1fc567b5e8","type": "pawn","x": 4,"y": 1,"player": 1,"firstMove": true,"queenSide": true,"kingSide": false},{"id": "5aeada9c-d57f-4371-ba38-455fc3661a74","type": "king","x": 4,"y": 0,"player": 1,"firstMove": true,"queenSide": true,"kingSide": false},{"id": "d931a2a6-375a-48aa-987f-eac7d4c45ca7","type": "pawn","x": 5,"y": 1,"player": 1,"firstMove": true,"queenSide": false,"kingSide": true},{"id": "06526081-95e9-4ccf-9b09-3fbc1668bb97","type": "bishop","x": 5,"y": 0,"player": 1,"queenSide": false,"kingSide": true},{"id": "bf7a7e14-e64f-4d53-9e2f-6041e25abc16","type": "pawn","x": 6,"y": 1,"player": 1,"firstMove": true,"queenSide": false,"kingSide": true},{"id": "db7fa161-6bc5-4867-b7a3-37e3b89b4233","type": "knight","x": 6,"y": 0,"player": 1,"queenSide": false,"kingSide": true},{"id": "3a959d27-1acc-422d-b6f0-557f22d99e9b","type": "pawn","x": 7,"y": 1,"player": 1,"firstMove": true,"queenSide": false,"kingSide": true},{"id": "3b492019-2751-49f5-932a-1d980d1bd4f3","type": "rook","x": 7,"y": 0,"player": 1,"firstMove": true,"queenSide": false,"kingSide": true}],"removedPieces": [[],[]],"enPassantTarget": {"x": 3,"y": 5},"allowNoKing": false,"aiSettings": [{"name": "Skill Level","value": 10},{"name": "Depth","value": 14},{"name": "Contempt","value": 21},{"name": "Analysis Contempt","value": "Both"},{"name": "MultiPV","value": 1},{"name": "Minimum Thinking Time","value": 20},{"name": "Slow Mover","value": 84},{"name": "UCI_Variant","value": "chess"},{"name": "Ponder","value": false},{"name": "UCI_Chess960","value": true},{"name": "UCI_AnalyseMode","value": true}]}