{"gameVersion": "1.1.12","gameId": "88f29b4e-f7af-4660-abeb-c17bb28fa58d","gameSavedAt": "2020-10-07T14:01:03.200Z","gameStartedAt": "2020-10-07T14:00:48.610Z","gameEndedAt": null,"totalTimePlayed": "PT14.109S","players": [{"playerId": null,"color": 0,"control": "Human"},{"playerId": null,"color": 1,"control": "Human"}],"currentTurn": 3,"pieces": [{"id": "d4e74136-b004-4c6e-bc9d-1b9948e64698","type": "pawn","x": 0,"y": 6,"player": 0,"firstMove": true,"queenSide": true,"kingSide": false},{"id": "651c7a42-7324-42e0-a326-1e78ac4b3a54","type": "rook","x": 0,"y": 7,"player": 0,"firstMove": true,"queenSide": true,"kingSide": false},{"id": "5f0d96fb-8b45-495c-94e0-0d4a5dd21e37","type": "pawn","x": 1,"y": 6,"player": 0,"firstMove": true,"queenSide": false,"kingSide": true},{"id": "7ef5cf04-37c2-49cf-88d2-66fa158f02d5","type": "knight","x": 1,"y": 7,"player": 0,"queenSide": false,"kingSide": true},{"id": "577a1bdb-19ab-48f2-8a82-badeeacbd727","type": "pawn","x": 2,"y": 6,"player": 0,"firstMove": true,"queenSide": false,"kingSide": true},{"id": "d27c9e81-f5a4-4b9c-8865-763467651fe2","type": "bishop","x": 2,"y": 7,"player": 0,"queenSide": false,"kingSide": true},{"id": "44c7da46-8afe-46e5-a3e8-b868b8c011fc","type": "pawn","x": 3,"y": 6,"player": 0,"firstMove": true,"queenSide": false,"kingSide": true},{"id": "255f331e-dd1f-4a3a-9467-6b98e75e1c9a","type": "queen","x": 3,"y": 7,"player": 0,"queenSide": false,"kingSide": true},{"id": "92dcd234-2d63-4ea9-9a52-f21ea2fa15a7","type": "pawn","x": 3,"y": 3,"player": 0,"firstMove": false,"queenSide": true,"kingSide": false},{"id": "b3431c15-84f5-4224-a9f7-7d21bde0878e","type": "king","x": 4,"y": 7,"player": 0,"firstMove": true,"queenSide": true,"kingSide": false},{"id": "d57a01bd-6579-43af-bd23-b72deacc9b52","type": "pawn","x": 5,"y": 6,"player": 0,"firstMove": true,"queenSide": false,"kingSide": true},{"id": "74481b7a-9881-40ec-9554-6430be5b6ee7","type": "bishop","x": 5,"y": 7,"player": 0,"queenSide": false,"kingSide": true},{"id": "2d3ad3f3-f82d-4ca8-a395-f5dc2e30c800","type": "pawn","x": 6,"y": 6,"player": 0,"firstMove": true,"queenSide": false,"kingSide": true},{"id": "44e26283-344f-4b0c-bd9c-2933776b5793","type": "knight","x": 6,"y": 7,"player": 0,"queenSide": false,"kingSide": true},{"id": "9067005c-f49e-4b5e-bced-517d759b4f22","type": "pawn","x": 7,"y": 6,"player": 0,"firstMove": true,"queenSide": false,"kingSide": true},{"id": "feecc654-490f-4a3d-a339-123a4debf55f","type": "rook","x": 7,"y": 7,"player": 0,"firstMove": true,"queenSide": false,"kingSide": true},{"id": "bd0328c0-a667-4c77-a218-ceeaa1ef724f","type": "pawn","x": 0,"y": 1,"player": 1,"firstMove": true,"queenSide": true,"kingSide": false},{"id": "794882be-6803-4ebf-a764-06ca106aa7d2","type": "rook","x": 0,"y": 0,"player": 1,"firstMove": true,"queenSide": true,"kingSide": false},{"id": "cffd9088-08d3-48b7-8f6b-4ffaf3f75b50","type": "pawn","x": 1,"y": 1,"player": 1,"firstMove": true,"queenSide": false,"kingSide": true},{"id": "95085ad7-72fc-4ea5-9f20-53d3d7b784be","type": "knight","x": 1,"y": 0,"player": 1,"queenSide": false,"kingSide": true},{"id": "9b621fd0-429b-46d7-a635-c3f98eee1848","type": "pawn","x": 2,"y": 1,"player": 1,"firstMove": true,"queenSide": false,"kingSide": true},{"id": "7e4f0eaa-7436-4509-b35d-933d2cd23948","type": "bishop","x": 2,"y": 0,"player": 1,"queenSide": false,"kingSide": true},{"id": "ef96ec76-6591-4a46-a9db-695ea868abdd","type": "queen","x": 3,"y": 0,"player": 1,"queenSide": false,"kingSide": true},{"id": "26662a0e-699e-4e0b-800b-7428b86a0734","type": "pawn","x": 4,"y": 1,"player": 1,"firstMove": true,"queenSide": true,"kingSide": false},{"id": "a08080f8-5d46-4520-82a4-70fb7213bc03","type": "king","x": 4,"y": 0,"player": 1,"firstMove": true,"queenSide": true,"kingSide": false},{"id": "7221b65a-2be6-4853-87f7-2b637452ff5f","type": "pawn","x": 5,"y": 1,"player": 1,"firstMove": true,"queenSide": false,"kingSide": true},{"id": "c6ee7236-2e56-4284-a256-2be98137ce42","type": "bishop","x": 5,"y": 0,"player": 1,"queenSide": false,"kingSide": true},{"id": "bf730a69-a956-4de5-b2f2-2897fbb10660","type": "pawn","x": 6,"y": 1,"player": 1,"firstMove": true,"queenSide": false,"kingSide": true},{"id": "22bd0e31-9843-4eb3-b3e1-7e036f21992f","type": "knight","x": 6,"y": 0,"player": 1,"queenSide": false,"kingSide": true},{"id": "bfbf92c1-6182-4e32-a93a-ea3c3d20cbf6","type": "pawn","x": 7,"y": 1,"player": 1,"firstMove": true,"queenSide": false,"kingSide": true},{"id": "ad72e75d-c9ff-4158-af7b-d85bb92a5ce3","type": "rook","x": 7,"y": 0,"player": 1,"firstMove": true,"queenSide": false,"kingSide": true}],"removedPieces": [[],[{"id": "059ae519-cca6-41b9-9ded-1894bc8b063b","type": "pawn","x": 3,"y": 3,"player": 1,"firstMove": false,"queenSide": false,"kingSide": true}]],"enPassantTarget": null,"allowNoKing": false,"aiSettings": [{"name": "Skill Level","value": 10},{"name": "Depth","value": 14},{"name": "Contempt","value": 21},{"name": "Analysis Contempt","value": "Both"},{"name": "MultiPV","value": 1},{"name": "Minimum Thinking Time","value": 20},{"name": "Slow Mover","value": 84},{"name": "UCI_Variant","value": "chess"},{"name": "Ponder","value": false},{"name": "UCI_Chess960","value": true},{"name": "UCI_AnalyseMode","value": true}]}