{"gameVersion": "1.1.12","gameId": "9b87b1e5-f532-4fdc-99ab-54762d26b958","gameSavedAt": "2021-04-06T19:21:55.025Z","gameStartedAt": "2021-04-06T19:21:45.835Z","gameEndedAt": null,"totalTimePlayed": "PT9.058S","players": [{"playerId": "86aadf7c-f3f0-4e0f-83b8-2c96f1048a74","color": 0,"control": "Human"},{"playerId": null,"color": 1,"control": "Human"}],"currentTurn": 2,"pieces": [{"id": "8b8fb251-5de1-4e4d-a0d5-6ad898211ca8","type": "pawn","x": 0,"y": 6,"player": 0,"firstMove": true,"queenSide": true,"kingSide": false},{"id": "de60899d-d55c-4acc-af34-dd519a7b38af","type": "rook","x": 0,"y": 7,"player": 0,"firstMove": true,"queenSide": true,"kingSide": false},{"id": "f7dfaa25-071b-4029-916a-8bcaea1a29a0","type": "pawn","x": 1,"y": 6,"player": 0,"firstMove": true,"queenSide": false,"kingSide": true},{"id": "dbd9eda0-e480-4229-8633-cfb280cfdfa2","type": "knight","x": 1,"y": 7,"player": 0,"queenSide": false,"kingSide": true},{"id": "f8a10e60-e3fc-4252-b556-2031bdc1d1e9","type": "pawn","x": 2,"y": 6,"player": 0,"firstMove": true,"queenSide": false,"kingSide": true},{"id": "88aa9f21-5cb5-4d4e-8d56-d8a4301696d0","type": "bishop","x": 2,"y": 7,"player": 0,"queenSide": false,"kingSide": true},{"id": "d83f8380-9d94-463b-88c8-0e157cc4e983","type": "pawn","x": 3,"y": 4,"player": 0,"firstMove": false,"queenSide": false,"kingSide": true},{"id": "8f563083-bfb6-4627-a65a-2dfa55ba1a7e","type": "queen","x": 3,"y": 7,"player": 0,"queenSide": false,"kingSide": true},{"id": "c4a4f4bc-e207-455c-a67a-e5dee6640e21","type": "pawn","x": 4,"y": 6,"player": 0,"firstMove": true,"queenSide": true,"kingSide": false},{"id": "84199935-9a40-4069-89f2-c9313511d7ae","type": "king","x": 4,"y": 7,"player": 0,"firstMove": true,"queenSide": true,"kingSide": false},{"id": "e3a95117-5e9a-4fd0-b854-a36f2ce695bf","type": "pawn","x": 5,"y": 6,"player": 0,"firstMove": true,"queenSide": false,"kingSide": true},{"id": "ed3dd34d-d1c3-433d-a4c8-238632c564b3","type": "bishop","x": 5,"y": 7,"player": 0,"queenSide": false,"kingSide": true},{"id": "11c7ecfe-2ffb-49ef-b38f-20f10d98098f","type": "pawn","x": 6,"y": 6,"player": 0,"firstMove": true,"queenSide": false,"kingSide": true},{"id": "635b7cf1-b44f-401b-a67b-6346149a6aee","type": "knight","x": 6,"y": 7,"player": 0,"queenSide": false,"kingSide": true},{"id": "209a6e08-b1c0-47b7-b097-e5920f6905c6","type": "pawn","x": 7,"y": 6,"player": 0,"firstMove": true,"queenSide": false,"kingSide": true},{"id": "07a2af76-9da4-4e42-98a5-5a1c5d30f6cc","type": "rook","x": 7,"y": 7,"player": 0,"firstMove": true,"queenSide": false,"kingSide": true},{"id": "6c562b40-1f9f-4977-8438-fe5dd7bd2f8e","type": "pawn","x": 0,"y": 1,"player": 1,"firstMove": true,"queenSide": true,"kingSide": false},{"id": "a9d7556e-8175-46bd-a95b-ea4c43c319f6","type": "rook","x": 0,"y": 0,"player": 1,"firstMove": true,"queenSide": true,"kingSide": false},{"id": "64000ff6-b60c-4129-bcd9-7303522c53a1","type": "pawn","x": 1,"y": 1,"player": 1,"firstMove": true,"queenSide": false,"kingSide": true},{"id": "1a7a735a-92e4-4b5d-8d9d-62004e9793d9","type": "knight","x": 1,"y": 0,"player": 1,"queenSide": false,"kingSide": true},{"id": "e303e5cb-49cc-4af1-b12f-1209580e9b8c","type": "pawn","x": 2,"y": 1,"player": 1,"firstMove": true,"queenSide": false,"kingSide": true},{"id": "6b761420-72a7-4300-b994-cd0af40e9ef2","type": "bishop","x": 2,"y": 0,"player": 1,"queenSide": false,"kingSide": true},{"id": "cd9a4244-a347-4402-bb64-2ea1693bcec0","type": "pawn","x": 3,"y": 3,"player": 1,"firstMove": false,"queenSide": false,"kingSide": true},{"id": "42d37ac9-0514-44a4-bff3-e4f478141728","type": "queen","x": 3,"y": 0,"player": 1,"queenSide": false,"kingSide": true},{"id": "419fcd24-ab9e-4f22-bac7-684287011293","type": "pawn","x": 4,"y": 1,"player": 1,"firstMove": true,"queenSide": true,"kingSide": false},{"id": "ddc0a555-7a3a-4ffc-9163-132b8589dc62","type": "king","x": 4,"y": 0,"player": 1,"firstMove": true,"queenSide": true,"kingSide": false},{"id": "ae2979f0-1771-44a1-856e-44dddb4a06d9","type": "pawn","x": 5,"y": 1,"player": 1,"firstMove": true,"queenSide": false,"kingSide": true},{"id": "3cfcbb98-c787-477b-8a3e-d1ef23c8d278","type": "bishop","x": 5,"y": 0,"player": 1,"queenSide": false,"kingSide": true},{"id": "a3031b78-468b-4e45-941d-a5196cd18b45","type": "pawn","x": 6,"y": 1,"player": 1,"firstMove": true,"queenSide": false,"kingSide": true},{"id": "6612b957-c0ad-466b-a29c-e57fd2463e88","type": "knight","x": 6,"y": 0,"player": 1,"queenSide": false,"kingSide": true},{"id": "3bf717f0-8ed4-40d9-9716-aab4e912195a","type": "pawn","x": 7,"y": 1,"player": 1,"firstMove": true,"queenSide": false,"kingSide": true},{"id": "a2b8ca69-168b-4fc3-aa7c-66caf10b21af","type": "rook","x": 7,"y": 0,"player": 1,"firstMove": true,"queenSide": false,"kingSide": true}],"removedPieces": [[],[]],"enPassantTarget": {"x": 3,"y": 2},"allowNoKing": false,"aiSettings": [{"name": "Skill Level","value": 10},{"name": "Depth","value": 14},{"name": "Contempt","value": 21},{"name": "Analysis Contempt","value": "Both"},{"name": "MultiPV","value": 1},{"name": "Minimum Thinking Time","value": 20},{"name": "Slow Mover","value": 84},{"name": "UCI_Variant","value": "chess"},{"name": "Ponder","value": false},{"name": "UCI_Chess960","value": true},{"name": "UCI_AnalyseMode","value": true}]}